{
  "race_id": "202505050312",
  "race_name": "3歳以上2勝クラス",
  "race_time": "2025-11-15 16:10",
  "race_place": "東京",
  "predictions": [
    {
      "rank": 1,
      "horse_id": "2021105859",
      "horse_name": "フォルラニーニ",
      "score": 0.4440594108713984,
      "horse_number": 8,
      "odds": 4.7
    },
    {
      "rank": 2,
      "horse_id": "2019105497",
      "horse_name": "アルゲンテウス",
      "score": 0.4435937469030655,
      "horse_number": 12,
      "odds": 7.0
    },
    {
      "rank": 3,
      "horse_id": "2022104814",
      "horse_name": "ダノンセンチュリー",
      "score": 0.38996170695458865,
      "horse_number": 6,
      "odds": 2.1
    },
    {
      "rank": 4,
      "horse_id": "2021105556",
      "horse_name": "ガルサブランカ",
      "score": 0.34590169589852093,
      "horse_number": 3,
      "odds": 11.1
    },
    {
      "rank": 5,
      "horse_id": "2021100564",
      "horse_name": "エフォートレス",
      "score": 0.27238114992051676,
      "horse_number": 2,
      "odds": 26.6
    },
    {
      "rank": 6,
      "horse_id": "2022105981",
      "horse_name": "ブラックルビー",
      "score": 0.1361526942257955,
      "horse_number": 5,
      "odds": 11.7
    },
    {
      "rank": 7,
      "horse_id": "2022105318",
      "horse_name": "コムユンプリュム",
      "score": 0.08690022307967456,
      "horse_number": 9,
      "odds": 13.6
    },
    {
      "rank": 8,
      "horse_id": "2021105415",
      "horse_name": "ドーンコーラス",
      "score": 0.03355782607160479,
      "horse_number": 11,
      "odds": 26.1
    },
    {
      "rank": 9,
      "horse_id": "2021100660",
      "horse_name": "ダイシンアポロン",
      "score": 0.013665275688496325,
      "horse_number": 4,
      "odds": 36.2
    },
    {
      "rank": 10,
      "horse_id": "2021103799",
      "horse_name": "ケイケイ",
      "score": -0.22309579128637466,
      "horse_number": 7,
      "odds": 43.3
    },
    {
      "rank": 11,
      "horse_id": "2021103486",
      "horse_name": "ホウオウシェリー",
      "score": -0.2542740227941147,
      "horse_number": 10,
      "odds": 28.2
    },
    {
      "rank": 12,
      "horse_id": "2019104761",
      "horse_name": "ジルバーン",
      "score": -0.35477131545877255,
      "horse_number": 13,
      "odds": 88.2
    },
    {
      "rank": 13,
      "horse_id": "2020101184",
      "horse_name": "シャイニースイフト",
      "score": -0.428744693697017,
      "horse_number": 1,
      "odds": 113.3
    }
  ]
}