{
  "race_id": "202503020707",
  "race_name": "3歳未勝利",
  "race_time": "2025-07-19 13:35",
  "race_place": "福島",
  "predictions": [
    {
      "rank": 1,
      "horse_id": "2022104275",
      "horse_name": "ノーブルライナー",
      "score": 0.22324125263043326,
      "horse_number": 1,
      "odds": 3.5
    },
    {
      "rank": 2,
      "horse_id": "2022102621",
      "horse_name": "リケアコンパンナ",
      "score": 0.133341551787623,
      "horse_number": 14,
      "odds": 4.8
    },
    {
      "rank": 3,
      "horse_id": "2022100836",
      "horse_name": "ライラックダンサー",
      "score": -0.008749429122516587,
      "horse_number": 15,
      "odds": 10.3
    },
    {
      "rank": 4,
      "horse_id": "2022110037",
      "horse_name": "フォルトレス",
      "score": -0.0444698884121415,
      "horse_number": 6,
      "odds": 16.0
    },
    {
      "rank": 5,
      "horse_id": "2022110025",
      "horse_name": "バーンズベリー",
      "score": -0.11248547724981171,
      "horse_number": 11,
      "odds": 10.2
    },
    {
      "rank": 6,
      "horse_id": "2022101700",
      "horse_name": "マハーギータ",
      "score": -0.1253333342937614,
      "horse_number": 13,
      "odds": 6.8
    },
    {
      "rank": 7,
      "horse_id": "2022100538",
      "horse_name": "リーサイェイ",
      "score": -0.18563273578105813,
      "horse_number": 4,
      "odds": 27.1
    },
    {
      "rank": 8,
      "horse_id": "2022101587",
      "horse_name": "クリアクォーツ",
      "score": -0.29558059381835994,
      "horse_number": 12,
      "odds": 24.4
    },
    {
      "rank": 9,
      "horse_id": "2022103561",
      "horse_name": "イオリ",
      "score": -0.4189249758462766,
      "horse_number": 10,
      "odds": 15.3
    },
    {
      "rank": 10,
      "horse_id": "2022109023",
      "horse_name": "ブルンツヴィーク",
      "score": -0.42070314076824655,
      "horse_number": 7,
      "odds": 19.5
    },
    {
      "rank": 11,
      "horse_id": "2022106302",
      "horse_name": "フェスティヴルキナ",
      "score": -0.5068805137775377,
      "horse_number": 9,
      "odds": 79.1
    },
    {
      "rank": 12,
      "horse_id": "2022106535",
      "horse_name": "エスプラネード",
      "score": -0.511764277666442,
      "horse_number": 3,
      "odds": 54.1
    },
    {
      "rank": 13,
      "horse_id": "2022105627",
      "horse_name": "プリヤンカー",
      "score": -0.5183588438690678,
      "horse_number": 8,
      "odds": 30.2
    },
    {
      "rank": 14,
      "horse_id": "2022109084",
      "horse_name": "ママアリガトー",
      "score": -0.5569455168514427,
      "horse_number": 16,
      "odds": 36.0
    },
    {
      "rank": 15,
      "horse_id": "2022100186",
      "horse_name": "シャンハイノハナ",
      "score": -0.5631146272095297,
      "horse_number": 2,
      "odds": 16.3
    },
    {
      "rank": 16,
      "horse_id": "2022102405",
      "horse_name": "ベルフォン",
      "score": -0.7329596672117042,
      "horse_number": 5,
      "odds": 82.4
    }
  ]
}