{
  "race_id": "202507050202",
  "race_name": "3歳以上1勝クラス",
  "race_time": "2025-12-07 10:35",
  "race_place": "中京",
  "predictions": [
    {
      "rank": 1,
      "horse_id": "2021107097",
      "horse_name": "ララバッカナール",
      "score": 0.44592116785991476,
      "horse_number": 12,
      "odds": 6.3
    },
    {
      "rank": 2,
      "horse_id": "2022102388",
      "horse_name": "ヒミノエトワール",
      "score": 0.10377707206676968,
      "horse_number": 7,
      "odds": 2.5
    },
    {
      "rank": 3,
      "horse_id": "2020105813",
      "horse_name": "マーゴットレーヴ",
      "score": 0.08368698254192854,
      "horse_number": 11,
      "odds": 12.5
    },
    {
      "rank": 4,
      "horse_id": "2022102952",
      "horse_name": "ユージュアーナ",
      "score": 0.023381999641606872,
      "horse_number": 14,
      "odds": 26.3
    },
    {
      "rank": 5,
      "horse_id": "2021104481",
      "horse_name": "ビアフォーナウ",
      "score": -0.006673405288489874,
      "horse_number": 9,
      "odds": 29.0
    },
    {
      "rank": 6,
      "horse_id": "2022105973",
      "horse_name": "ハヤブサオヒメサマ",
      "score": -0.036622818607396614,
      "horse_number": 1,
      "odds": 14.8
    },
    {
      "rank": 7,
      "horse_id": "2022101108",
      "horse_name": "ホウオウショコラ",
      "score": -0.1249648765327092,
      "horse_number": 13,
      "odds": 11.8
    },
    {
      "rank": 8,
      "horse_id": "2022102631",
      "horse_name": "ハイゼンスレイ",
      "score": -0.2120798078248586,
      "horse_number": 4,
      "odds": 17.9
    },
    {
      "rank": 9,
      "horse_id": "2022102026",
      "horse_name": "アクアマリーナ",
      "score": -0.22662039104192022,
      "horse_number": 16,
      "odds": 5.7
    },
    {
      "rank": 10,
      "horse_id": "2022101649",
      "horse_name": "ウィンターサン",
      "score": -0.22973642490965512,
      "horse_number": 6,
      "odds": 14.8
    },
    {
      "rank": 11,
      "horse_id": "2021103723",
      "horse_name": "アンリーベイビー",
      "score": -0.2499106273349862,
      "horse_number": 3,
      "odds": 16.4
    },
    {
      "rank": 12,
      "horse_id": "2021103325",
      "horse_name": "カレンナオトメ",
      "score": -0.3042858627695777,
      "horse_number": 2,
      "odds": 95.4
    },
    {
      "rank": 13,
      "horse_id": "2021105125",
      "horse_name": "リヤンドゥミラクル",
      "score": -0.321233323355741,
      "horse_number": 15,
      "odds": 106.3
    },
    {
      "rank": 14,
      "horse_id": "2021103484",
      "horse_name": "エコロカレン",
      "score": -0.5244467230032313,
      "horse_number": 10,
      "odds": 93.2
    },
    {
      "rank": 15,
      "horse_id": "2021102303",
      "horse_name": "カンカール",
      "score": -0.5485661685169994,
      "horse_number": 8,
      "odds": 99.3
    },
    {
      "rank": 16,
      "horse_id": "2021106394",
      "horse_name": "ワキノノーブル",
      "score": -0.5756804866807193,
      "horse_number": 5,
      "odds": 164.1
    }
  ]
}