[
  {
    "race_id": "202605010601",
    "race_name": "3歳未勝利",
    "distance": 1300,
    "track_surface": 2,
    "race_place": "東京",
    "race_grade": 9,
    "race_date": "2026-02-15",
    "race_time": "2026-02-15 10:05:00 +0900"
  },
  {
    "race_id": "202605010602",
    "race_name": "3歳未勝利",
    "distance": 2100,
    "track_surface": 2,
    "race_place": "東京",
    "race_grade": 9,
    "race_date": "2026-02-15",
    "race_time": "2026-02-15 10:35:00 +0900"
  },
  {
    "race_id": "202605010603",
    "race_name": "3歳新馬",
    "distance": 1600,
    "track_surface": 2,
    "race_place": "東京",
    "race_grade": 8,
    "race_date": "2026-02-15",
    "race_time": "2026-02-15 11:05:00 +0900"
  },
  {
    "race_id": "202605010604",
    "race_name": "3歳1勝クラス",
    "distance": 1600,
    "track_surface": 2,
    "race_place": "東京",
    "race_grade": 7,
    "race_date": "2026-02-15",
    "race_time": "2026-02-15 11:35:00 +0900"
  },
  {
    "race_id": "202605010605",
    "race_name": "3歳未勝利",
    "distance": 1800,
    "track_surface": 1,
    "race_place": "東京",
    "race_grade": 9,
    "race_date": "2026-02-15",
    "race_time": "2026-02-15 12:25:00 +0900"
  },
  {
    "race_id": "202605010606",
    "race_name": "4歳以上1勝クラス",
    "distance": 2400,
    "track_surface": 1,
    "race_place": "東京",
    "race_grade": 7,
    "race_date": "2026-02-15",
    "race_time": "2026-02-15 12:55:00 +0900"
  },
  {
    "race_id": "202605010607",
    "race_name": "4歳以上1勝クラス",
    "distance": 1400,
    "track_surface": 2,
    "race_place": "東京",
    "race_grade": 7,
    "race_date": "2026-02-15",
    "race_time": "2026-02-15 13:25:00 +0900"
  },
  {
    "race_id": "202605010608",
    "race_name": "4歳以上2勝クラス",
    "distance": 1600,
    "track_surface": 1,
    "race_place": "東京",
    "race_grade": 6,
    "race_date": "2026-02-15",
    "race_time": "2026-02-15 13:55:00 +0900"
  },
  {
    "race_id": "202605010609",
    "race_name": "雲雀S",
    "distance": 1600,
    "track_surface": 1,
    "race_place": "東京",
    "race_grade": 5,
    "race_date": "2026-02-15",
    "race_time": "2026-02-15 14:25:00 +0900"
  },
  {
    "race_id": "202605010610",
    "race_name": "バレンタイン",
    "distance": 1400,
    "track_surface": 2,
    "race_place": "東京",
    "race_grade": 4,
    "race_date": "2026-02-15",
    "race_time": "2026-02-15 15:01:00 +0900"
  },
  {
    "race_id": "202605010611",
    "race_name": "共同通信杯",
    "distance": 1800,
    "track_surface": 1,
    "race_place": "東京",
    "race_grade": 3,
    "race_date": "2026-02-15",
    "race_time": "2026-02-15 15:45:00 +0900"
  },
  {
    "race_id": "202605010612",
    "race_name": "4歳以上2勝クラス",
    "distance": 1400,
    "track_surface": 2,
    "race_place": "東京",
    "race_grade": 6,
    "race_date": "2026-02-15",
    "race_time": "2026-02-15 16:25:00 +0900"
  },
  {
    "race_id": "202608020601",
    "race_name": "3歳未勝利",
    "distance": 1800,
    "track_surface": 2,
    "race_place": "京都",
    "race_grade": 9,
    "race_date": "2026-02-15",
    "race_time": "2026-02-15 09:55:00 +0900"
  },
  {
    "race_id": "202608020602",
    "race_name": "3歳新馬",
    "distance": 1200,
    "track_surface": 2,
    "race_place": "京都",
    "race_grade": 8,
    "race_date": "2026-02-15",
    "race_time": "2026-02-15 10:25:00 +0900"
  },
  {
    "race_id": "202608020603",
    "race_name": "3歳未勝利",
    "distance": 1400,
    "track_surface": 2,
    "race_place": "京都",
    "race_grade": 9,
    "race_date": "2026-02-15",
    "race_time": "2026-02-15 10:55:00 +0900"
  },
  {
    "race_id": "202608020604",
    "race_name": "3歳1勝クラス",
    "distance": 1900,
    "track_surface": 2,
    "race_place": "京都",
    "race_grade": 7,
    "race_date": "2026-02-15",
    "race_time": "2026-02-15 11:25:00 +0900"
  },
  {
    "race_id": "202608020605",
    "race_name": "3歳未勝利",
    "distance": 2000,
    "track_surface": 1,
    "race_place": "京都",
    "race_grade": 9,
    "race_date": "2026-02-15",
    "race_time": "2026-02-15 12:15:00 +0900"
  },
  {
    "race_id": "202608020606",
    "race_name": "3歳未勝利",
    "distance": 1600,
    "track_surface": 1,
    "race_place": "京都",
    "race_grade": 9,
    "race_date": "2026-02-15",
    "race_time": "2026-02-15 12:45:00 +0900"
  },
  {
    "race_id": "202608020607",
    "race_name": "4歳以上1勝クラス",
    "distance": 1800,
    "track_surface": 2,
    "race_place": "京都",
    "race_grade": 7,
    "race_date": "2026-02-15",
    "race_time": "2026-02-15 13:15:00 +0900"
  },
  {
    "race_id": "202608020608",
    "race_name": "4歳以上1勝クラス",
    "distance": 2000,
    "track_surface": 1,
    "race_place": "京都",
    "race_grade": 7,
    "race_date": "2026-02-15",
    "race_time": "2026-02-15 13:45:00 +0900"
  },
  {
    "race_id": "202608020609",
    "race_name": "春日特別",
    "distance": 1800,
    "track_surface": 1,
    "race_place": "京都",
    "race_grade": 6,
    "race_date": "2026-02-15",
    "race_time": "2026-02-15 14:15:00 +0900"
  },
  {
    "race_id": "202608020610",
    "race_name": "北山S",
    "distance": 1800,
    "track_surface": 2,
    "race_place": "京都",
    "race_grade": 5,
    "race_date": "2026-02-15",
    "race_time": "2026-02-15 14:50:00 +0900"
  },
  {
    "race_id": "202608020611",
    "race_name": "京都記念",
    "distance": 2200,
    "track_surface": 1,
    "race_place": "京都",
    "race_grade": 2,
    "race_date": "2026-02-15",
    "race_time": "2026-02-15 15:30:00 +0900"
  },
  {
    "race_id": "202608020612",
    "race_name": "4歳以上2勝クラス",
    "distance": 1200,
    "track_surface": 2,
    "race_place": "京都",
    "race_grade": 6,
    "race_date": "2026-02-15",
    "race_time": "2026-02-15 16:10:00 +0900"
  },
  {
    "race_id": "202610010801",
    "race_name": "3歳未勝利",
    "distance": 1700,
    "track_surface": 2,
    "race_place": "小倉",
    "race_grade": 9,
    "race_date": "2026-02-15",
    "race_time": "2026-02-15 09:45:00 +0900"
  },
  {
    "race_id": "202610010802",
    "race_name": "3歳未勝利",
    "distance": 1200,
    "track_surface": 1,
    "race_place": "小倉",
    "race_grade": 9,
    "race_date": "2026-02-15",
    "race_time": "2026-02-15 10:15:00 +0900"
  },
  {
    "race_id": "202610010803",
    "race_name": "4歳以上1勝クラス",
    "distance": 1000,
    "track_surface": 2,
    "race_place": "小倉",
    "race_grade": 7,
    "race_date": "2026-02-15",
    "race_time": "2026-02-15 10:45:00 +0900"
  },
  {
    "race_id": "202610010805",
    "race_name": "3歳未勝利",
    "distance": 1800,
    "track_surface": 1,
    "race_place": "小倉",
    "race_grade": 9,
    "race_date": "2026-02-15",
    "race_time": "2026-02-15 12:05:00 +0900"
  },
  {
    "race_id": "202610010806",
    "race_name": "4歳以上1勝クラス",
    "distance": 2000,
    "track_surface": 1,
    "race_place": "小倉",
    "race_grade": 7,
    "race_date": "2026-02-15",
    "race_time": "2026-02-15 12:35:00 +0900"
  },
  {
    "race_id": "202610010807",
    "race_name": "4歳以上1勝クラス",
    "distance": 2600,
    "track_surface": 1,
    "race_place": "小倉",
    "race_grade": 7,
    "race_date": "2026-02-15",
    "race_time": "2026-02-15 13:05:00 +0900"
  },
  {
    "race_id": "202610010808",
    "race_name": "4歳以上1勝クラス",
    "distance": 2400,
    "track_surface": 2,
    "race_place": "小倉",
    "race_grade": 7,
    "race_date": "2026-02-15",
    "race_time": "2026-02-15 13:35:00 +0900"
  },
  {
    "race_id": "202610010809",
    "race_name": "太宰府特別",
    "distance": 2000,
    "track_surface": 1,
    "race_place": "小倉",
    "race_grade": 6,
    "race_date": "2026-02-15",
    "race_time": "2026-02-15 14:05:00 +0900"
  },
  {
    "race_id": "202610010810",
    "race_name": "大濠特別",
    "distance": 1200,
    "track_surface": 1,
    "race_place": "小倉",
    "race_grade": 6,
    "race_date": "2026-02-15",
    "race_time": "2026-02-15 14:40:00 +0900"
  },
  {
    "race_id": "202610010811",
    "race_name": "北九州短距離",
    "distance": 1200,
    "track_surface": 1,
    "race_place": "小倉",
    "race_grade": 4,
    "race_date": "2026-02-15",
    "race_time": "2026-02-15 15:15:00 +0900"
  },
  {
    "race_id": "202610010812",
    "race_name": "4歳以上1勝クラス",
    "distance": 1700,
    "track_surface": 2,
    "race_place": "小倉",
    "race_grade": 7,
    "race_date": "2026-02-15",
    "race_time": "2026-02-15 16:01:00 +0900"
  }
]